pytqshacl/__init__.py
pytqshacl/cli.py
pytqshacl/config.py
pytqshacl/run.py
pytqshacl/topquadrant/__init__.py
pytqshacl/topquadrant/install.py
pytqshacl/topquadrant/bin/shacl-1.4.4/shacl-1.4.4/log4j2.properties
pytqshacl/topquadrant/bin/shacl-1.4.4/shacl-1.4.4/lib/RoaringBitmap-1.3.0.jar
pytqshacl/topquadrant/bin/shacl-1.4.4/shacl-1.4.4/lib/caffeine-3.1.8.jar
pytqshacl/topquadrant/bin/shacl-1.4.4/shacl-1.4.4/lib/collection-0.7.jar
pytqshacl/topquadrant/bin/shacl-1.4.4/shacl-1.4.4/lib/commons-codec-1.17.1.jar
pytqshacl/topquadrant/bin/shacl-1.4.4/shacl-1.4.4/lib/commons-collections4-4.4.jar
pytqshacl/topquadrant/bin/shacl-1.4.4/shacl-1.4.4/lib/commons-compress-1.27.1.jar
pytqshacl/topquadrant/bin/shacl-1.4.4/shacl-1.4.4/lib/commons-csv-1.12.0.jar
pytqshacl/topquadrant/bin/shacl-1.4.4/shacl-1.4.4/lib/commons-io-2.17.0.jar
pytqshacl/topquadrant/bin/shacl-1.4.4/shacl-1.4.4/lib/commons-lang3-3.17.0.jar
pytqshacl/topquadrant/bin/shacl-1.4.4/shacl-1.4.4/lib/error_prone_annotations-2.27.0.jar
pytqshacl/topquadrant/bin/shacl-1.4.4/shacl-1.4.4/lib/gson-2.11.0.jar
pytqshacl/topquadrant/bin/shacl-1.4.4/shacl-1.4.4/lib/jakarta.json-2.0.1.jar
pytqshacl/topquadrant/bin/shacl-1.4.4/shacl-1.4.4/lib/jcl-over-slf4j-2.0.16.jar
pytqshacl/topquadrant/bin/shacl-1.4.4/shacl-1.4.4/lib/jena-arq-5.2.0.jar
pytqshacl/topquadrant/bin/shacl-1.4.4/shacl-1.4.4/lib/jena-base-5.2.0.jar
pytqshacl/topquadrant/bin/shacl-1.4.4/shacl-1.4.4/lib/jena-core-5.2.0.jar
pytqshacl/topquadrant/bin/shacl-1.4.4/shacl-1.4.4/lib/jena-iri-5.2.0.jar
pytqshacl/topquadrant/bin/shacl-1.4.4/shacl-1.4.4/lib/libthrift-0.21.0.jar
pytqshacl/topquadrant/bin/shacl-1.4.4/shacl-1.4.4/lib/log4j-api-2.24.3.jar
pytqshacl/topquadrant/bin/shacl-1.4.4/shacl-1.4.4/lib/log4j-core-2.24.3.jar
pytqshacl/topquadrant/bin/shacl-1.4.4/shacl-1.4.4/lib/log4j-slf4j2-impl-2.24.3.jar
pytqshacl/topquadrant/bin/shacl-1.4.4/shacl-1.4.4/lib/protobuf-java-4.28.2.jar
pytqshacl/topquadrant/bin/shacl-1.4.4/shacl-1.4.4/lib/shacl-1.4.4.jar
pytqshacl-141.dist-info/METADATA
pytqshacl-141.dist-info/WHEEL
pytqshacl-141.dist-info/entry_points.txt
pytqshacl-141.dist-info/RECORD
