Metadata-Version: 2.4
Name: pytqshacl
Version: 141
Summary: Python wrapper around TopQuadrant SHACL processor
Author-email: Majid alDosari <majid.aldosari@pnnl.gov>, Majid alDosari <majidaldosari-github@yahoo.com>
Provides-Extra: cli
Requires-Dist: fire; extra == 'cli'
Provides-Extra: java
Requires-Dist: install-jdk; extra == 'java'
